icpd/__init__.py
icpd/__main__.py
icpd/__version__.py
icpd/constants.py
icpd/exceptions.py
icpd/exif_datetime.py
icpd/logger.py
icpd/photo_asset_ext.py
icpd/py.typed
icpd/string_helpers.py
icpd/utils.py
icpd-0.0.1a1.dist-info/LICENSE
icpd-0.0.1a1.dist-info/METADATA
icpd-0.0.1a1.dist-info/WHEEL
icpd-0.0.1a1.dist-info/entry_points.txt
icpd-0.0.1a1.dist-info/top_level.txt
icpd-0.0.1a1.dist-info/RECORD
